langgraph_checkpoint_kurrentdb/__init__.py
langgraph_checkpoint_kurrentdb/tracing.py
langgraph_checkpoint_kurrentdb-0.1.3.dist-info/LICENSE.md
langgraph_checkpoint_kurrentdb-0.1.3.dist-info/METADATA
langgraph_checkpoint_kurrentdb-0.1.3.dist-info/WHEEL
langgraph_checkpoint_kurrentdb-0.1.3.dist-info/RECORD
