Metadata-Version: 2.3
Name: langgraph_checkpoint_kurrentdb
Version: 0.1.3
Summary: KurrentDB checkpoint implementation for LangGraph
Author: Lougarou
Author-email: yogisawesome@gmail.com
Requires-Python: >=3.12,<4.0
Classifier: Programming Language :: Python :: 3
Classifier: Programming Language :: Python :: 3.12
Classifier: Programming Language :: Python :: 3.13
Requires-Dist: kurrentdbclient (>=1.0b4,<2.0)
Requires-Dist: langchain-core (>=0.1.0)
Requires-Dist: langgraph (>=0.0.15)
Requires-Dist: langgraph-checkpoint (>=2.0.15,<3.0.0)
Requires-Dist: matplotlib (>=3.0.0)
Requires-Dist: notebook (>=7.4.0,<8.0.0)
Requires-Dist: opentelemetry-api (>=1.20.0)
Requires-Dist: opentelemetry-exporter-otlp-proto-grpc (>=1.20.0)
Requires-Dist: opentelemetry-sdk (>=1.20.0)
Requires-Dist: pandas (>=2.0.0)
